{
  "utf-8": {
    "korean": [],
    "english": [
      "kkkkDang",
      "Mind",
      "Char",
      "Index",
      "Title",
      "Contents",
      "korea",
      "MIND",
      "CHAR",
      "MIND",
      "CHAR",
      "MIND",
      "CHAR",
      "MIND",
      "CHAR",
      "MIND",
      "CHAR",
      "MIND",
      "CHAR",
      "MIND",
      "CHAR",
      "MIND",
      "CHAR",
      "MIND",
      "CHAR",
      "MIND",
      "CHAR",
      "MIND",
      "CHAR",
      "MIND",
      "CHAR",
      "MIND",
      "CHAR",
      "MIND",
      "CHAR",
      "MIND",
      "CHAR",
      "MIND",
      "CHAR",
      "MIND",
      "CHAR"
    ]
  },
  "cp949": {
    "korean": [
      "심성궁은",
      "열두가지",
      "날짐승",
      "길짐승에",
      "비유를",
      "인간의",
      "자질을",
      "점쳐본",
      "것입니다",
      "당신이",
      "상상의",
      "복스럽고",
      "징조의",
      "상징임",
      "다음과",
      "가집니다",
      "너그럽고",
      "거짓이",
      "없으며",
      "마음이",
      "바르고",
      "심성궁은",
      "열두가지",
      "날짐승",
      "길짐승에",
      "비유를",
      "인간의",
      "자질을",
      "점쳐본",
      "것입니다",
      "당신이",
      "다음과",
      "가집니다",
      "위엄이",
      "용감하면서도",
      "있습니다",
      "타협이나",
      "굽힘이",
      "성격도",
      "심성궁은",
      "열두가지",
      "날짐승",
      "길짐승에",
      "비유를",
      "인간의",
      "자질을",
      "점쳐본",
      "것입니다",
      "당신이",
      "다음과",
      "가집니다",
      "자신을",
      "과소평가하는",
      "경향이",
      "있습니다",
      "때문에",
      "자신감이나",
      "진취성도",
      "부족한",
      "심성궁은",
      "열두가지",
      "날짐승",
      "길짐승에",
      "비유를",
      "인간의",
      "자질을",
      "점쳐본",
      "것입니다",
      "당신이",
      "다음과",
      "가집니다",
      "자신을",
      "과소평가하는",
      "경향이",
      "있습니다",
      "때문에",
      "자신감이나",
      "진취성도",
      "부족한",
      "심성궁은",
      "열두가지",
      "날짐승",
      "길짐승에",
      "비유를",
      "인간의",
      "자질을",
      "점쳐본",
      "것입니다",
      "당신이",
      "다음과",
      "가집니다",
      "총명하고",
      "재주가",
      "많지만",
      "경박한",
      "있습니다",
      "신중하지",
      "못하다면",
      "심성궁은",
      "열두가지"
    ],
    "english": [
      "kDang",
      "Mind",
      "Char",
      "Index",
      "Title",
      "Contents",
      "korea",
      "MIND",
      "CHAR",
      "MIND",
      "CHAR",
      "MIND",
      "CHAR",
      "MIND",
      "CHAR",
      "MIND",
      "CHAR",
      "MIND",
      "CHAR",
      "MIND",
      "CHAR",
      "MIND",
      "CHAR",
      "MIND",
      "CHAR",
      "MIND",
      "CHAR",
      "MIND",
      "CHAR",
      "MIND",
      "CHAR",
      "MIND",
      "CHAR",
      "MIND",
      "CHAR",
      "MIND",
      "CHAR",
      "MIND",
      "CHAR",
      "MIND",
      "CHAR"
    ]
  },
  "euc-kr": {
    "korean": [
      "심성궁은",
      "열두가지",
      "날짐승",
      "길짐승에",
      "비유를",
      "인간의",
      "자질을",
      "점쳐본",
      "것입니다",
      "당신이",
      "상상의",
      "복스럽고",
      "징조의",
      "상징임",
      "다음과",
      "가집니다",
      "너그럽고",
      "거짓이",
      "없으며",
      "마음이",
      "바르고",
      "심성궁은",
      "열두가지",
      "날짐승",
      "길짐승에",
      "비유를",
      "인간의",
      "자질을",
      "점쳐본",
      "것입니다",
      "당신이",
      "다음과",
      "가집니다",
      "위엄이",
      "용감하면서도",
      "있습니다",
      "타협이나",
      "굽힘이",
      "성격도",
      "심성궁은",
      "열두가지",
      "날짐승",
      "길짐승에",
      "비유를",
      "인간의",
      "자질을",
      "점쳐본",
      "것입니다",
      "당신이",
      "다음과",
      "가집니다",
      "자신을",
      "과소평가하는",
      "경향이",
      "있습니다",
      "때문에",
      "자신감이나",
      "진취성도",
      "부족한",
      "심성궁은",
      "열두가지",
      "날짐승",
      "길짐승에",
      "비유를",
      "인간의",
      "자질을",
      "점쳐본",
      "것입니다",
      "당신이",
      "다음과",
      "가집니다",
      "자신을",
      "과소평가하는",
      "경향이",
      "있습니다",
      "때문에",
      "자신감이나",
      "진취성도",
      "부족한",
      "심성궁은",
      "열두가지",
      "날짐승",
      "길짐승에",
      "비유를",
      "인간의",
      "자질을",
      "점쳐본",
      "것입니다",
      "당신이",
      "다음과",
      "가집니다",
      "총명하고",
      "재주가",
      "많지만",
      "경박한",
      "있습니다",
      "신중하지",
      "못하다면",
      "심성궁은",
      "열두가지"
    ],
    "english": [
      "kkkkDang",
      "Mind",
      "Char",
      "Index",
      "Title",
      "Contents",
      "korea",
      "MIND",
      "CHAR",
      "MIND",
      "CHAR",
      "MIND",
      "CHAR",
      "MIND",
      "CHAR",
      "MIND",
      "CHAR",
      "MIND",
      "CHAR",
      "MIND",
      "CHAR",
      "MIND",
      "CHAR",
      "MIND",
      "CHAR",
      "MIND",
      "CHAR",
      "MIND",
      "CHAR",
      "MIND",
      "CHAR",
      "MIND",
      "CHAR",
      "MIND",
      "CHAR",
      "MIND",
      "CHAR",
      "MIND",
      "CHAR",
      "MIND",
      "CHAR"
    ]
  },
  "latin1": {
    "korean": [],
    "english": [
      "kDang",
      "Mind",
      "Char",
      "Index",
      "Title",
      "Contents",
      "korea",
      "MIND",
      "CHAR",
      "MIND",
      "CHAR",
      "MIND",
      "CHAR",
      "MIND",
      "CHAR",
      "MIND",
      "CHAR",
      "MIND",
      "CHAR",
      "MIND",
      "CHAR",
      "MIND",
      "CHAR",
      "MIND",
      "CHAR",
      "MIND",
      "CHAR",
      "MIND",
      "CHAR",
      "MIND",
      "CHAR",
      "MIND",
      "CHAR",
      "MIND",
      "CHAR",
      "MIND",
      "CHAR",
      "MIND",
      "CHAR",
      "MIND",
      "CHAR"
    ]
  }
}