{
  "generated_at": "2026-03-10T00:46:11Z",
  "global": {
    "success_count": 25,
    "failure_count": 0,
    "retry_count": 0
  },
  "programs": {
    "lifeunse": {
      "collection": "saju_raw_lifeunse",
      "documents_attempted": 0,
      "success_count": 0,
      "failure_count": 0,
      "errors": []
    },
    "sajubaekgwa": {
      "collection": "saju_raw_sajubaekgwa",
      "documents_attempted": 0,
      "success_count": 0,
      "failure_count": 0,
      "errors": []
    },
    "sajudosa": {
      "collection": "saju_raw_sajudosa",
      "documents_attempted": 25,
      "success_count": 25,
      "failure_count": 0,
      "errors": []
    },
    "sajunara": {
      "collection": "saju_raw_sajunara",
      "documents_attempted": 0,
      "success_count": 0,
      "failure_count": 0,
      "errors": []
    }
  }
}